[["facebook.com",{"p":[["http://www.@/l.php",87056],["http://www.@",33768],["http://m.@/l.php",19597],["http://www.@/home.php",1047],["http://m.@",530],["http://m.@/home.php",159],["http://touch.@/l.php",50]],"c":143708,"se":false}],["stumbleupon.com",{"p":[["http://www.@",70380]],"c":70380,"se":true}],["yahoo.net",{"p":[["http://36ohk6dgmcd1n-c.c.yom.mail.@/om/api/1.0/openmail.app.invoke/36ohk6dgmcd1n/11/1.0.35/us/en-US/view.html/0",44431],["http://36ohk6dgmcd1n-c.c.yom.mail.@/om/api/1.0/openmail.app.invoke/36ohk6dgmcd1n/11/1.0.35/aa/en-SG/view.html/0",2266],["http://36ohk6dgmcd1n-c.c.yom.mail.@/om/api/1.0/openmail.app.invoke/36ohk6dgmcd1n/11/1.0.35/ca/en-CA/view.html/0",2030],["http://36ohk6dgmcd1n-c.c.yom.mail.@/om/api/1.0/openmail.app.invoke/36ohk6dgmcd1n/11/1.0.35/uk/en-GB/view.html/0",1889],["http://36ohk6dgmcd1n-c.c.yom.mail.@/om/api/1.0/openmail.app.invoke/36ohk6dgmcd1n/11/1.0.35/xe/en-JO/view.html/0",1516],["http://36ohk6dgmcd1n-c.c.yom.mail.@/om/api/1.0/openmail.app.invoke/36ohk6dgmcd1n/11/1.0.35/es/es-ES/view.html/0",860],["http://36ohk6dgmcd1n-c.c.yom.mail.@/om/api/1.0/openmail.app.invoke/36ohk6dgmcd1n/11/1.0.35/gr/el-GR/view.html/0",858],["http://36ohk6dgmcd1n-c.c.yom.mail.@/om/api/1.0/openmail.app.invoke/36ohk6dgmcd1n/11/1.0.35/au/en-AU/view.html/0",834],["http://36ohk6dgmcd1n-c.c.yom.mail.@/om/api/1.0/openmail.app.invoke/36ohk6dgmcd1n/11/1.0.35/uk_bt/en-GB-x-bt/view.html/0",712],["http://36ohk6dgmcd1n-c.c.yom.mail.@/om/api/1.0/openmail.app.invoke/36ohk6dgmcd1n/11/1.0.35/ca_rogers/en-CA-x-rogers/view.html/0",571],["http://36ohk6dgmcd1n-c.c.yom.mail.@/om/api/1.0/openmail.app.invoke/36ohk6dgmcd1n/11/1.0.35/us_sbc/en-US-x-sbc/view.html/0",562],["http://36ohk6dgmcd1n-c.c.yom.mail.@/om/api/1.0/openmail.app.invoke/36ohk6dgmcd1n/11/1.0.35/in/en-IN/view.html/0",532],["http://36ohk6dgmcd1n-c.c.yom.mail.@/om/api/1.0/openmail.app.invoke/36ohk6dgmcd1n/11/1.0.35/fr/fr-FR/view.html/0",378],["http://36ohk6dgmcd1n-c.c.yom.mail.@/om/api/1.0/openmail.app.invoke/36ohk6dgmcd1n/11/1.0.35/us_verizon/en-US-x-verizon/view.html/0",367],["http://36ohk6dgmcd1n-c.c.yom.mail.@/om/api/1.0/openmail.app.invoke/36ohk6dgmcd1n/11/1.0.35/de/de-DE/view.html/0",366],["http://36ohk6dgmcd1n-c.c.yom.mail.@/om/api/1.0/openmail.app.invoke/36ohk6dgmcd1n/11/1.0.35/br/pt-BR/view.html/0",325],["http://36ohk6dgmcd1n-c.c.yom.mail.@/om/api/1.0/openmail.app.invoke/36ohk6dgmcd1n/11/1.0.35/sg/en-SG/view.html/0",233],["http://36ohk6dgmcd1n-c.c.yom.mail.@/om/api/1.0/openmail.app.invoke/36ohk6dgmcd1n/11/1.0.35/e1/es-US/view.html/0",181],["http://36ohk6dgmcd1n-c.c.yom.mail.@/om/api/1.0/openmail.app.invoke/36ohk6dgmcd1n/11/1.0.35/ar/es-AR/view.html/0",161],["http://36ohk6dgmcd1n-c.c.yom.mail.@/om/api/1.0/openmail.app.invoke/36ohk6dgmcd1n/11/1.0.35/us_ftr/en-US-x-ftr/view.html/0",155],["http://36ohk6dgmcd1n-c.c.yom.mail.@/om/api/1.0/openmail.app.invoke/36ohk6dgmcd1n/11/1.0.35/mx/es-MX/view.html/0",140],["http://36ohk6dgmcd1n-c.c.yom.mail.@/om/api/1.0/openmail.app.invoke/36ohk6dgmcd1n/11/1.0.35/it/it-IT/view.html/0",104],["http://36ohk6dgmcd1n-c.c.yom.mail.@/om/api/1.0/openmail.app.invoke/36ohk6dgmcd1n/11/1.0.35/nz_tnz/en-NZ-x-tnz/view.html/0",99],["http://36ohk6dgmcd1n-c.c.yom.mail.@/om/api/1.0/openmail.app.invoke/36ohk6dgmcd1n/11/1.0.35/nz/en-NZ/view.html/0",93],["http://36ohk6dgmcd1n-c.c.yom.mail.@/om/api/1.0/openmail.app.invoke/36ohk6dgmcd1n/11/1.0.35/us_bizmail/en-US/view.html/0",64],["http://36ohk6dgmcd1n-c.c.yom.mail.@/om/api/1.0/openmail.app.invoke/36ohk6dgmcd1n/11/1.0.35/cf/fr-CA/view.html/0",56]],"c":61246,"se":false}],["google.com",{"p":[["http://www.@",46765]],"c":46778,"se":true}],["yonkis.com",{"p":[["http://www.@",45947],["http://www.@/index.php",208]],"c":46158,"se":false}],["yahoo.com",{"p":[["http://us.mg5.mail.@/neo/launch",3428],["http://us.mg4.mail.@/neo/launch",3158],["http://us.mg6.mail.@/neo/launch",2948],["http://www.@",2154],["http://us.mg3.mail.@/neo/launch",1089],["http://us.mg203.mail.@/dc/launch",969],["http://us.mg204.mail.@/dc/launch",929],["http://us.mg205.mail.@/dc/launch",925],["http://us.mg1.mail.@/neo/launch",705],["http://xe.mg40.mail.@/neo/launch",534],["http://us.mg201.mail.@/dc/launch",431],["http://us.mg205.mail.@/dc/blank.html",374],["http://us.mg203.mail.@/dc/blank.html",349],["http://us.mg204.mail.@/dc/blank.html",328],["http://us.mc1620.mail.@/mc/welcome",257],["http://us.mc1614.mail.@/mc/welcome",254],["http://uk.mg40.mail.@/neo/launch",244],["http://us.mc1617.mail.@/mc/welcome",239],["http://us.mc1613.mail.@/mc/welcome",231],["http://us.mc1612.mail.@/mc/welcome",221],["http://us.mc1610.mail.@/mc/welcome",210],["http://us.mc1618.mail.@/mc/welcome",209],["http://us.mg201.mail.@/dc/blank.html",203],["http://us.mc1621.mail.@/mc/welcome",198],["http://us.mc1616.mail.@/mc/welcome",192],["http://us.mc1615.mail.@/mc/welcome",186],["http://us.mc1205.mail.@/mc/welcome",184],["http://us.mc1619.mail.@/mc/welcome",183],["http://uk.mg.bt.mail.@/neo/launch",183],["http://aa.mg5.mail.@/neo/launch",182],["http://us.mc659.mail.@/mc/welcome",182],["http://us.mg205.mail.@/neo/launch",177],["http://us.mg2.mail.@/neo/launch",171],["http://us.mc1623.mail.@/mc/welcome",162],["http://aa.mg6.mail.@/neo/launch",154],["http://us.mc1622.mail.@/mc/welcome",154],["http://us.mc1607.mail.@/mc/welcome",152],["http://us.mc1603.mail.@/mc/welcome",135],["http://us.mc1845.mail.@/mc/welcome",130],["http://us.mc1133.mail.@/mc/welcome",129],["http://us.mc1803.mail.@/mc/welcome",129],["http://ca.mg206.mail.@/neo/launch",125],["http://us.mc845.mail.@/mc/welcome",125],["http://us.mc1801.mail.@/mc/welcome",124],["http://us.mc1844.mail.@/mc/welcome",122],["http://us.mc839.mail.@/mc/welcome",122],["http://us.mc1847.mail.@/mc/welcome",120],["http://aa.mg4.mail.@/neo/launch",119],["http://us.mc1606.mail.@/mc/welcome",117],["http://us.mc394.mail.@/mc/welcome",114],["http://uk.mg41.mail.@/neo/launch",114],["http://us.mc393.mail.@/mc/welcome",108],["http://us.mc1814.mail.@/mc/welcome",108],["http://us.mc1260.mail.@/mc/welcome",107],["http://us.mc1609.mail.@/mc/welcome",106],["http://us.mc1601.mail.@/mc/welcome",106],["http://us.mc1809.mail.@/mc/welcome",106],["http://us.mc1201.mail.@/mc/welcome",105],["http://us.mc838.mail.@/mc/welcome",104],["http://us.mc1254.mail.@/mc/welcome",104],["http://us.mc1117.mail.@/mc/welcome",104],["http://us.mc1301.mail.@/mc/welcome",104],["http://us.mc1605.mail.@/mc/welcome",103],["http://us.mc1800.mail.@/mc/welcome",103],["http://us.mc1257.mail.@/mc/welcome",102],["http://ca.mg6.mail.@/neo/launch",102],["http://us.mc1608.mail.@/mc/welcome",101],["http://us.mc837.mail.@/mc/welcome",100],["http://us.mg206.mail.@/dc/launch",100],["http://ca.mg4.mail.@/neo/launch",100],["http://us.mc1802.mail.@/mc/welcome",98],["http://us.mc1206.mail.@/mc/welcome",98],["http://us.mc800.mail.@/mc/welcome",96],["http://us.mc1202.mail.@/mc/welcome",96],["http://ca.mg5.mail.@/neo/launch",96],["http://in.mg61.mail.@/neo/launch",94],["http://us.mc1807.mail.@/mc/welcome",91],["http://us.mc1806.mail.@/mc/welcome",90],["http://us.mc1817.mail.@/mc/welcome",89],["http://us.mc1147.mail.@/mc/welcome",88],["http://us.mc1302.mail.@/mc/welcome",88],["http://us.mc1255.mail.@/mc/welcome",86],["http://es.mg40.mail.@/neo/launch",85],["http://us.mc1207.mail.@/mc/welcome",83],["http://us.mc1815.mail.@/mc/welcome",83],["http://us.mc1200.mail.@/mc/welcome",83],["http://3cp9lcoq32dpn-c.c.yom.mail.@/om/api/1.0/openmail.app.invoke/3cp9lcoq32dpn/77/1.0.35/us/en-US/blank.html/0",82],["http://us.mc1209.mail.@/mc/welcome",82],["http://us.mc1811.mail.@/mc/welcome",81],["http://us.mc1624.mail.@/mc/welcome",80],["http://us.mc1214.mail.@/mc/welcome",80],["http://us.mc1617.mail.@/mc/showMessage",77],["http://us.mc1256.mail.@/mc/welcome",77],["http://us.mc1813.mail.@/mc/welcome",76],["http://us.mc1203.mail.@/mc/welcome",75],["http://us.mc1124.mail.@/mc/welcome",75],["http://us.mc1403.mail.@/mc/welcome",75],["http://us.mc1204.mail.@/mc/welcome",74],["http://us.mc1805.mail.@/mc/welcome",73],["http://us.mc1810.mail.@/mc/welcome",73],["http://us.mc1604.mail.@/mc/welcome",72],["http://us.mc1218.mail.@/mc/welcome",71],["http://us.mc1140.mail.@/mc/welcome",70],["http://us.mc836.mail.@/mc/welcome",70],["http://us.mc1215.mail.@/mc/welcome",70],["http://us.mg4.mail.@/dc/launch",69],["http://us.mc1804.mail.@/mc/welcome",68],["http://us.mc1216.mail.@/mc/welcome",68],["http://us.mc1102.mail.@/mc/welcome",68],["http://us.mc655.mail.@/mc/welcome",67],["http://us.mc1614.mail.@/mc/showMessage",67],["http://us.mc1143.mail.@/mc/welcome",67],["http://us.mc1612.mail.@/mc/showMessage",66],["http://us.mc1645.mail.@/mc/welcome",66],["http://us.mc1108.mail.@/mc/welcome",66],["http://us.mc1613.mail.@/mc/showMessage",65],["http://us.mc1628.mail.@/mc/welcome",64],["http://us.mc1618.mail.@/mc/showMessage",64],["http://us.mc1217.mail.@/mc/welcome",64],["http://us.mc1259.mail.@/mc/welcome",63],["http://us.mc1610.mail.@/mc/showMessage",62],["http://us.mc1138.mail.@/mc/welcome",62],["http://us.mc834.mail.@/mc/welcome",62],["http://es.mg41.mail.@/neo/launch",62],["http://us.mc1406.mail.@/mc/welcome",61],["http://us.mc833.mail.@/mc/welcome",60],["http://au.mg6.mail.@/neo/launch",60],["http://us.mc1620.mail.@/mc/showMessage",60],["http://us.mg206.mail.@/dc/blank.html",59],["http://us.mc1258.mail.@/mc/welcome",59],["http://us.mc447.mail.@/mc/welcome",59],["http://gr.mg40.mail.@/neo/launch",59],["http://us.mc1812.mail.@/mc/welcome",57],["http://us.mc1808.mail.@/mc/welcome",57],["http://aa.mg3.mail.@/neo/launch",57],["http://us.mc835.mail.@/mc/welcome",57],["http://us.mc1616.mail.@/mc/showMessage",56],["http://us.mc1261.mail.@/mc/welcome",56],["http://us.mc1110.mail.@/mc/welcome",55],["http://us.mc1626.mail.@/mc/welcome",53],["http://us.mc1135.mail.@/mc/welcome",52],["http://us.mc1134.mail.@/mc/welcome",52],["http://us.mc807.mail.@/mc/welcome",52],["http://us.mc1141.mail.@/mc/welcome",52],["http://us.mc1145.mail.@/mc/welcome",52],["http://us.mc1211.mail.@/mc/welcome",52],["http://us.mc1631.mail.@/mc/welcome",51],["http://us.mc658.mail.@/mc/welcome",51],["http://us.mc1118.mail.@/mc/welcome",51],["http://us.mc1627.mail.@/mc/welcome",50]],"c":43273,"se":true}],["live.com",{"p":[["http://www.@",35027]],"c":35027,"se":true}],["reddit.com",{"p":[["http://www.@/r/WTF/",10700],["http://www.@/r/AskReddit/comments/uua77/whats_the_biggest_mindfuck_youve_ever_heard/",8312],["http://www.@/r/trees/comments/vb8g6/im_not_a_big_fan_of_those_blew_my_mind_posts_but/",2585],["http://www.@",1064],["http://www.@/r/science/",878],["http://www.@/r/todayilearned/",432],["http://www.@/r/AskReddit/comments/utthk/scientists_of_reddit_what_misconceptions_do_us/",392],["http://www.@/r/Minecraft/comments/uvcj4/136112_yottaparsecs_away_from_earth_and_i_still/",250],["http://www.@/r/wtf",183],["http://www.@/r/WTF",181],["http://www.@/r/WTF/top/",163],["http://www.@/new/",141],["http://www.@/r/space/",137],["http://www.@/r/space",110],["http://www.@/toolbar/inner",107],["http://www.@/r/science",96],["http://www.@/r/WTF/new/",68],["http://www.@/r/AskReddit/comments/ubyxy/what_concept_or_idea_do_you_find_impossible_to/",61],["http://www.@/r/AskReddit/comments/rrmhm/whats_a_little_known_website_everyone_should_know/",56]],"c":27377,"se":false}],["t.co",{"p":[["http://@/oVEbjllk",2186],["http://@/wCiet6GE",826],["http://@/NXvPKpEu",761],["http://@/PNZECVrT",401],["http://@/NjCfFlyg",363],["http://@/ZqDldNW8",295],["http://@/9bsLvqyJ",273],["http://@/kMmlVn1N",243],["http://@/rj2QIRzI",240],["http://@/QPVOzbX8",238],["http://@/Gl3w7Twg",237],["http://@/vyLPy3qO",181],["http://@/ICJ4Xq85",170],["http://@/GLlwpiGS",127],["http://@/hqX8TP8J",126],["http://@/Ax0MkkpP",98],["http://@/17qFm227",90],["http://@/QcGlvTKI",81],["http://@/2wqOqw14",77],["http://@/r6c9SkBZ",76],["http://@/wUnJAO9z",69],["http://@/rFRuo9c9",69],["http://@/Gf01Lz4o",68],["http://@/ASs9BdW6",56]],"c":14224,"se":false}],["youtube.com",{"p":[["http://www.@/watch",8694],["http://www.@/user/jacknjellify",88],["http://www.@/user/carykh",53]],"c":9017,"se":false}],["scale2.s3.amazonaws.com",{"p":[["http://@/c.swf",4665],["http://@/scale2.swf",3877],["http://@/scale2lang.swf",219]],"c":8761,"se":false}],["aol.com",{"p":[["http://mail.@/36451-111/aol-6/en-us/Suite.aspx",581],["http://mail.@/36301-111/aol-6/en-us/Suite.aspx",503],["http://mail.@/36210-111/aol-6/en-us/Suite.aspx",500],["http://mail.@/36478-111/aol-6/en-us/Suite.aspx",482],["http://mail.@/36396-111/aol-6/en-us/Suite.aspx",319],["http://mail.@/36294-111/aol-6/en-us/Suite.aspx",282],["http://mail.@/36451-111/aol-6/en-us/mail/DisplayMessage.aspx",147],["http://mail.@/36301-111/aol-6/en-us/mail/DisplayMessage.aspx",124],["http://mail.@/36451-111/aol-6/en-us/Lite/MsgRead.aspx",123],["http://mail.@/36210-111/aol-6/en-us/mail/DisplayMessage.aspx",109],["http://mail.@/36478-111/aol-6/en-us/mail/DisplayMessage.aspx",105],["http://cpw.mail.@/34561-111/talktalk-5/en-gb/Suite.aspx",104],["http://mail.@/36478-111/aol-6/en-us/Lite/MsgRead.aspx",92],["http://mail.@/36210-111/aol-6/en-us/Lite/MsgRead.aspx",92],["http://mail.@/36301-111/aol-6/en-us/Lite/MsgRead.aspx",91],["http://mail.@/36396-111/aol-6/en-us/mail/DisplayMessage.aspx",86],["http://mail.@/36210-111/aol-6/en-us/suite.aspx",76],["http://www.@",67],["http://mail.@/36294-111/aol-6/en-us/Lite/MsgRead.aspx",63],["http://mail.@/36451-111/aol-6/en-us/suite.aspx",61],["http://mail.@/36294-111/aol-6/en-us/mail/DisplayMessage.aspx",60],["http://mail.@/36396-111/aol-6/en-us/Lite/MsgRead.aspx",60],["http://mail.@/36301-111/aol-6/en-us/suite.aspx",56],["http://mail.@/36255-111/aol-6/en-us/Lite/MsgRead.aspx",52]],"c":5096,"se":true}],["vk.com",{"p":[["http://@/feed",1349],["http://@/im",652],["http://@/mail",112],["http://@/mr",100]],"c":5063,"se":false}],["comcast.net",{"p":[["http://web.mail.@/zimbra/mail",145]],"c":5054,"se":false}],["vkmag.com",{"p":[["http://www.@",2646],["http://www.@/magazine/wat_denk_je_wel_niet_dat_je_bent/",211],["http://www.@/magazine/page/P16/",199],["http://www.@/magazine/page/P32/",57]],"c":3204,"se":false}],["go.com",{"p":[["http://www.@",3108]],"c":3108,"se":true}],["tcmag.com",{"p":[["http://www.@",2660],["http://www.@/magazine/page/P22",100]],"c":2913,"se":false}],["itaringa.net",{"p":[["http://links.@/go",2858]],"c":2858,"se":false}],["nasa.gov",{"p":[["http://apod.@/apod/ap120312.html",1248],["http://apod.@/apod/image/1203/scaleofuniverse_huang.swf",982],["http://heasarc.@/docs/cosmic/",67]],"c":2379,"se":false}],["surfingbird.ru",{"p":[["http://@",909],["http://@/surf/zms2C48C",753],["http://@/surf/GRAE4EE0",367]],"c":2059,"se":false}],["bodybuilding.com",{"p":[["http://forum.@/showthread.php",2055]],"c":2056,"se":false}],["awaker.net",{"p":[["http://www.@/plug/q.htm",1841]],"c":1841,"se":false}],["bearfood.com",{"p":[["http://@/queue",622],["http://@/archives/2012-05-22",477],["http://@/links/queue/sort:score/direction:desc",256],["http://@/l/111/the_scale_of_the_universe",233],["http://@/links/queue/page:2",73]],"c":1814,"se":false}],["tumblr.com",{"p":[["http://www.@/dashboard",519],["http://boho-f-l-o-w.@/links",66]],"c":1680,"se":false}],["bing.com",{"p":[["http://www.@",1349]],"c":1349,"se":true}],["verizon.com",{"p":[["http://mail.@/webmail/driver",1315]],"c":1334,"se":false}],["imgur.com",{"p":[["http://@/gallery/0BUgL",828],["http://@/gallery/imAQL",215],["http://@/gallery/lupnE",90]],"c":1230,"se":false}],["funnyjunk.com",{"p":[["http://@/channel/fucking-science/The+scale+of+the+universe/LBaXGYO/",404],["http://www.@/channel/fucking-science/The+scale+of+the+universe/LBaXGYO/",386],["http://www.@/channel/fucking-science/Scale+of+the+Universe/uuoXGhh/",61]],"c":1211,"se":false}],["uni-watch.com",{"p":[["http://www.@",585],["http://www.@/2012/06/20/charlotte-bobcats-unveil-new-uniforms/",83],["http://www.@/2012/06/22/a-look-at-players-whove-worn-zero-and-double-zero/",62],["http://www.@/2012/06/21/rays-unveil-1979-fauxback/",51]],"c":1129,"se":false}],["zipfm.lt",{"p":[["http://www.@",437],["http://@",221],["http://www.@/transliacija-internetu",87],["http://www.@/muzika",54]],"c":1106,"se":false}],["pgr21.com",{"p":[["http://www.@/zboard4/zboard.php",683],["http://@/zboard4/zboard.php",415]],"c":1098,"se":false}],["politiken.dk",{"p":[["http://@/tjek/ECE1657376/saadan-bliver-du-sat-paa-plads-af-universet/",1050]],"c":1050,"se":false}],["malgusto.com",{"p":[["http://www.@",616],["http://www.@/page/2/",90]],"c":961,"se":false}],["blogfa.com",{"p":[],"c":907,"se":false}],["leprosorium.ru",{"p":[["http://@",649],["http://@/comments/1308724",184]],"c":903,"se":false}],["wordpress.com",{"p":[["http://mathmunch.@/games/",106]],"c":898,"se":false}],["taringa.net",{"p":[["http://www.@/posts/ciencia-educacion/15023815/La-escala-del-universo-_Esta-pagina-web-no-la-debes-perder_.html",133],["http://www.@/posts/animaciones/15099373/La-escala-del-Universo.html",117],["http://www.@/posts/ciencia-educacion/15007568/Mira-El-tamano-de-las-Cosas_-Reales_.html",108],["http://www.@/posts/ciencia-educacion/15007670/El-tamano-de-las-cosas-en-una-web.html",99],["http://www.@/posts/ciencia-educacion/13863126/La-Escala-del-Universo---Muy-Buena-animacion_.html",86],["http://www.@/posts/noticias/14330044/_Cual-es-el-mejor-Navegador-y-el-mas-usado_.html",60]],"c":836,"se":false}],["longurl.org",{"p":[["http://@",821]],"c":821,"se":false}],["scaleofuniverse.com",{"p":[["http://@",762]],"c":812,"se":false}],["windowsforum.kr",{"p":[["http://@/3370009",725]],"c":742,"se":false}],["samharris.org",{"p":[["http://www.@",602]],"c":726,"se":false}],["rouming.cz",{"p":[["http://www.@/roumingLinkShow.php",713]],"c":725,"se":false}],["tuenti.com",{"p":[["http://www.@",666]],"c":724,"se":false}],["ar15.com",{"p":[["http://www.@/forums/t_1_5/1331580_Scale_of_the_Universe.html",692]],"c":705,"se":false}],["shuud.mn",{"p":[["http://www.@/%d0%b3%d0%b0%d0%b9%d1%85%d0%b0%d0%bc%d1%88%d0%b8%d0%b3%d1%82%d0%b0%d0%b9-%d0%b1%d0%b0%d1%81-%d0%b6%d0%b8%d1%85%d2%af%d2%af%d0%b4%d1%8d%d1%81-%d1%82%d3%a9%d1%80%d3%a9%d0%bc-%d0%be%d1%80%d1%87%d0%bb/",689]],"c":692,"se":false}],["earthlink.net",{"p":[["http://webmail.@/wam/msg.jsp",439],["http://webmail.c.@/wam/msg.jsp",163]],"c":684,"se":false}],["twitter.com",{"p":[["http://@",277],["https://@/samharrisorg/status/213498747991240704",79]],"c":663,"se":false}],["lj-toys.com",{"p":[["http://@",649]],"c":649,"se":false}],["juno.com",{"p":[["http://webmaila.@/webmail/new/5",145],["http://webmailb.@/webmail/new/5",107],["http://webmaila.@/webmail/new/8",86],["http://webmaila.@/webmail/new/21",71],["http://webmailb.@/webmail/new/8",68]],"c":637,"se":false}],["wikispaces.com",{"p":[["http://stviateur2012.@/St-Viateur+English+Club",165],["http://emslegacy.@",136]],"c":607,"se":false}],["synacor.com",{"p":[],"c":599,"se":false}],["livejournal.com",{"p":[["http://sl-lopatnikov.@/667622.html",100],["http://mi3ch.@",65]],"c":597,"se":false}],["noojoomi.com",{"p":[["http://@/%D8%B4%DA%AF%D9%81%D8%AA-%D8%B2%D8%AF%D9%87-%D8%AE%D9%88%D8%A7%D9%87%DB%8C%D8%AF-%D8%B4%D8%AF.html",330],["http://@/\\xd8\\xb4\\xda\\xaf\\xd9\\x81\\xd8\\xaa-\\xd8\\xb2\\xd8\\xaf\\xd9\\x87-\\xd8\\xae\\xd9\\x88\\xd8\\xa7\\xd9\\x87\\xdb\\x8c\\xd8\\xaf-\\xd8\\xb4\\xd8\\xaf.html",99],["http://@/%d8%b4%da%af%d9%81%d8%aa-%d8%b2%d8%af%d9%87-%d8%ae%d9%88%d8%a7%d9%87%db%8c%d8%af-%d8%b4%d8%af-2.html",80],["http://@/%d8%b4%da%af%d9%81%d8%aa-%d8%b2%d8%af%d9%87-%d8%ae%d9%88%d8%a7%d9%87%db%8c%d8%af-%d8%b4%d8%af.html",56]],"c":593,"se":false}],["baztab.net",{"p":[["http://@/fa/news/8830/%d8%aa%d8%b5%d9%88%db%8c%d8%b1-%d8%af%db%8c%d8%af%d9%86%db%8c-%d9%88-%d8%b4%da%af%d9%81%d8%aa%db%8c-%d8%a2%d9%88%d8%b1-%d8%a7%d8%b2-%d8%ac%d9%87%d8%a7%d9%86-%d8%a7%d8%b2-%2210-%d8%a8%d9%87-%d8%aa%d9%88%d8%a7%d9%86-35-%22-%d8%aa%d8%a7-%2210-%d8%a8%d9%87-%d8%aa%d9%88%d8%a7%d9%86-27%22",432],["http://www.@/fa/news/8830/%d8%aa%d8%b5%d9%88%db%8c%d8%b1-%d8%af%db%8c%d8%af%d9%86%db%8c-%d9%88-%d8%b4%da%af%d9%81%d8%aa%db%8c-%d8%a2%d9%88%d8%b1-%d8%a7%d8%b2-%d8%ac%d9%87%d8%a7%d9%86-%d8%a7%d8%b2-%2210-%d8%a8%d9%87-%d8%aa%d9%88%d8%a7%d9%86-35-%22-%d8%aa%d8%a7-%2210-%d8%a8%d9%87-%d8%aa%d9%88%d8%a7%d9%86-27%22",99]],"c":578,"se":false}],["boards.ie",{"p":[["http://www.@/vbulletin/showthread.php",533]],"c":570,"se":false}],["mediavida.com",{"p":[["http://www.@/foro/90/increible-apli-web-donde-puedes-ver-insignifi-451211",361],["http://www.@/foro/6/increible-apli-web-donde-puedes-ver-insignifi-451211",84],["http://www.@/foro/90/hilo-imagenes-increibles-432341/42",74]],"c":539,"se":false}],["itsbx.com",{"p":[["http://@",355],["http://www.@",176]],"c":533,"se":false}],["pantip.com",{"p":[["http://www.@/cafe/wahkor/topic/X12285007/X12285007.html",525]],"c":528,"se":false}]]